aic_tools/__init__.py
aic_tools/datetime.py
tools/__init__.py
tools/datetime.py
aic_tools-1.1.0.dist-info/METADATA
aic_tools-1.1.0.dist-info/WHEEL
aic_tools-1.1.0.dist-info/top_level.txt
aic_tools-1.1.0.dist-info/RECORD
