Metadata-Version: 2.1
Name: aic-tools
Version: 1.1.0
Summary: Tools for AI Characters
Home-page: UNKNOWN
Author: Viacheslav Kovalevskyi
Author-email: viacheslav@kovalevskyi.com
License: MIT
Platform: UNKNOWN
Requires-Dist: crewai-tools (==0.1)
